inference/__init__.py
inference/code/__init__.py
inference/code/algo1_inference.py
inference/code/algo2_inference.py
inference/code/algo2_inference_utils.py
inference/code/config.py
inference/code/csku.py
inference/code/download_updated_model_files.py
inference/code/inference.py
inference/code/inference_config.py
inference/code/model.py
inference/code/utils.py
inference/code/inference_utils/__init__.py
inference/code/inference_utils/bbox.py
inference/code/inference_utils/colors.py
inference/code/inference_utils/inference_support_fns.py
inference/code/inference_utils/utils.py
kwik24_ai_combination_sku-0.0.2.dist-info/METADATA
kwik24_ai_combination_sku-0.0.2.dist-info/WHEEL
kwik24_ai_combination_sku-0.0.2.dist-info/top_level.txt
kwik24_ai_combination_sku-0.0.2.dist-info/RECORD
