Metadata-Version: 2.1
Name: kwik24-ai-combination-sku
Version: 0.0.2
Summary: Combination SKU
Home-page: https://bitbucket.org/kwik24/kwik24_ai
Author: Santosh Kumar Waddi
Author-email: santosh.waddi@bigbasket.com
License: UNKNOWN
Platform: UNKNOWN
Classifier: Programming Language :: Python :: 3
Classifier: Operating System :: OS Independent
Requires-Python: >=3.6
